pyam/__init__.py
pyam/_version.py
pyam/cohort.py
pyam/config.py
pyam/config_manager.py
pyam/cunit.py
pyam/files.py
pyam/pam.py
pyam/run_pytest.py
pyam/template-template.xlsx
pyam/test_manifest.py
pyam/cmd/__init__.py
pyam/cmd/args.py
pyam/cmd/cohort.py
pyam/cmd/config.py
pyam/cmd/extract_downloads.py
pyam/cmd/find_duplicates.py
pyam/cmd/generate_template.py
pyam/cmd/github_push.py
pyam/cmd/github_retrieve.py
pyam/cmd/init.py
pyam/cmd/mark.py
pyam/cmd/run.py
pyam/cmd/write_csv.py
pyam/fixtures/__init__.py
pyam/fixtures/clang.py
pyam/fixtures/common.py
pyam/fixtures/python.py
pyam/fixtures/vhdl.py
pyam/fixtures/xlsx.py
pyAutoMark-0.8.2.dist-info/LICENSE
pyAutoMark-0.8.2.dist-info/METADATA
pyAutoMark-0.8.2.dist-info/WHEEL
pyAutoMark-0.8.2.dist-info/entry_points.txt
pyAutoMark-0.8.2.dist-info/top_level.txt
pyAutoMark-0.8.2.dist-info/RECORD
