Metadata-Version: 2.1
Name: pyAutoMark
Version: 0.8.2
Summary: Automated marking of student electronic submissions
Author-email: John Williams <j.a.r.williams@jarw.org.uk>
License: GPL-3.0-openpyxl
Project-URL: Repository, https://github.com/willijar/pyAutoMark
Project-URL: Homepage, https://willijar.github.io/pyAutoMark/
Keywords: pytest,assessment
Classifier: Development Status :: 4 - Beta
Classifier: Operating System :: OS Independent
Classifier: Programming Language :: Python :: 3.10
Classifier: Programming Language :: C
Classifier: Framework :: Pytest
Classifier: Topic :: Education :: Testing
Classifier: Intended Audience :: Education
Classifier: License :: OSI Approved :: GNU General Public License v3 or later (GPLv3+)
Requires-Python: >=3.10
License-File: LICENSE
Requires-Dist: openpyxl >=3.1.2
Requires-Dist: pytest >=7.3.2
Requires-Dist: pytest-timeout >=2.1.0
